{"青岛市":{"visited":true,"notes":"2025-11-16-17\n2025-1-11-13\n2025-5-1-5\n2025-7-22-24\n2025-10-1-2"},"开封市":{"visited":true,"notes":"2025-12-5-7\n柠檬的：\n开封像一匹黑马，去之前根本没有想到会这么好玩。好久没有见到小羊了，特别开心，在路上那几个小时觉得特别漫长，怎么还没到怎么还没到，但是一点都没有累的感觉，这种开心很不一样，别的事情带不来这种感受，我很喜欢这种幸福感。都说越长大那越值得开心的事就越少，越长大就越不容易开心，还好，还好，有小羊出现，把我从本该无趣而琐碎的日子里打捞出来。我好感想我的男朋友，虽然有的时候也会拌嘴，但是和他在一起，我会体验到前所未尝的滋味，无论是酸是甜，这件事本身就让我感到幸福。说回开封本身，我很喜欢那里的园区，没去迪士尼，先去了中国迪士尼，希望咱们有一天去迪士尼相拥看烟花漫天！这里感觉适合玩个3-4天的，感觉还有一些没发掘到,微微遗憾，但总的来说很完美。西安也是这样，但是感觉上确实开封要更还原，好像更美一点。当时在那个银色建筑的地方，听完唱歌，顺着人流往外走，小羊拉着我的手，那个时候有一种可靠的感觉，不知道为什么，感觉人海茫茫，大家都在互相拥挤，但是有一个人可以和我一起，在大冬天也感觉很温暖。但是我是一个有分离焦虑的人，我对那些为数不多我可依赖的人，一旦要分离我就会提前好久开始焦虑难安，我一想到要离开小羊，又回到那个每天忙碌的学校，自己坐车自己操心，只剩自己了，我就好难过。希望，有一天，普通的一天，我们买了小蛋糕，是为了庆祝，结束异地。"}}